{
  "surah": {
    "number": 96,
    "name": "العلق",
    "englishName": "Al-Alaq",
    "totalAyat": 19,
    "revelationType": "Meccan",
    "meaning": "العلقة"
  },
  "ayat": [
    {
      "number": 1,
      "text": "بِسْمِ ٱللَّهِ ٱلرَّحْمَٰنِ ٱلرَّحِيمِ ٱقْرَأْ بِٱسْمِ رَبِّكَ ٱلَّذِى خَلَقَ",
      "juz": 30,
      "page": 597,
      "tafsir": {
        "muyassar": "اقرأ -أيها النبي- ما أُنزل إليك من القرآن مُفْتَتِحًا باسم ربك المتفرد بالخلق، الذي خلق كل إنسان من قطعة دم غليظ أحمر. اقرأ -أيها النبي- ما أُنزل إليك، وإن ربك لكثير الإحسان واسع الجود، الذي علَّم خلقه الكتابة بالقلم، علَّم الإنسان ما لم يكن يعلم، ونقله من ظلمة الجهل إلى نور العلم.",
        "mukhtasar": "",
        "saadi": "",
        "jalalayn": ""
      },
      "gharib": {
        "muyassar": {},
        "siraj": {}
      },
      "video": {
        "videoId": "enNduVCQjeo",
        "title": "برنامج غريب القرآن || الحلقة 38 - { بسم الله مجرىها }",
        "url": "https://www.youtube.com/watch?v=enNduVCQjeo",
        "keyword": "بسم الله مجرىها"
      }
    },
    {
      "number": 2,
      "text": "خَلَقَ ٱلْإِنسَٰنَ مِنْ عَلَقٍ",
      "juz": 30,
      "page": 597,
      "tafsir": {
        "muyassar": "اقرأ -أيها النبي- ما أُنزل إليك من القرآن مُفْتَتِحًا باسم ربك المتفرد بالخلق، الذي خلق كل إنسان من قطعة دم غليظ أحمر. اقرأ -أيها النبي- ما أُنزل إليك، وإن ربك لكثير الإحسان واسع الجود، الذي علَّم خلقه الكتابة بالقلم، علَّم الإنسان ما لم يكن يعلم، ونقله من ظلمة الجهل إلى نور العلم.",
        "mukhtasar": "",
        "saadi": "",
        "jalalayn": ""
      },
      "gharib": {
        "muyassar": {},
        "siraj": {}
      },
      "video": {
        "videoId": "mcXnCCGNPLs",
        "title": "#برنامج_غريب_القرآن || الحلقة 111 - { إن الإنسان خلق هلوعًا }",
        "url": "https://www.youtube.com/watch?v=mcXnCCGNPLs",
        "keyword": "إن الإنسان خلق هلوعًا"
      }
    },
    {
      "number": 3,
      "text": "ٱقْرَأْ وَرَبُّكَ ٱلْأَكْرَمُ",
      "juz": 30,
      "page": 597,
      "tafsir": {
        "muyassar": "اقرأ -أيها النبي- ما أُنزل إليك من القرآن مُفْتَتِحًا باسم ربك المتفرد بالخلق، الذي خلق كل إنسان من قطعة دم غليظ أحمر. اقرأ -أيها النبي- ما أُنزل إليك، وإن ربك لكثير الإحسان واسع الجود، الذي علَّم خلقه الكتابة بالقلم، علَّم الإنسان ما لم يكن يعلم، ونقله من ظلمة الجهل إلى نور العلم.",
        "mukhtasar": "",
        "saadi": "",
        "jalalayn": ""
      },
      "gharib": {
        "muyassar": {},
        "siraj": {}
      },
      "video": {
        "videoId": "02iZa0vqNG4",
        "title": "#برنامج_غريب_القرآن || الحلقة 78 - { وما يعزب عن ربك }",
        "url": "https://www.youtube.com/watch?v=02iZa0vqNG4",
        "keyword": "وما يعزب عن ربك"
      }
    },
    {
      "number": 4,
      "text": "ٱلَّذِى عَلَّمَ بِٱلْقَلَمِ",
      "juz": 30,
      "page": 597,
      "tafsir": {
        "muyassar": "اقرأ -أيها النبي- ما أُنزل إليك من القرآن مُفْتَتِحًا باسم ربك المتفرد بالخلق، الذي خلق كل إنسان من قطعة دم غليظ أحمر. اقرأ -أيها النبي- ما أُنزل إليك، وإن ربك لكثير الإحسان واسع الجود، الذي علَّم خلقه الكتابة بالقلم، علَّم الإنسان ما لم يكن يعلم، ونقله من ظلمة الجهل إلى نور العلم.",
        "mukhtasar": "",
        "saadi": "",
        "jalalayn": ""
      },
      "gharib": {
        "muyassar": {},
        "siraj": {}
      }
    },
    {
      "number": 5,
      "text": "عَلَّمَ ٱلْإِنسَٰنَ مَا لَمْ يَعْلَمْ",
      "juz": 30,
      "page": 597,
      "tafsir": {
        "muyassar": "اقرأ -أيها النبي- ما أُنزل إليك من القرآن مُفْتَتِحًا باسم ربك المتفرد بالخلق، الذي خلق كل إنسان من قطعة دم غليظ أحمر. اقرأ -أيها النبي- ما أُنزل إليك، وإن ربك لكثير الإحسان واسع الجود، الذي علَّم خلقه الكتابة بالقلم، علَّم الإنسان ما لم يكن يعلم، ونقله من ظلمة الجهل إلى نور العلم.",
        "mukhtasar": "",
        "saadi": "",
        "jalalayn": ""
      },
      "gharib": {
        "muyassar": {},
        "siraj": {}
      }
    },
    {
      "number": 6,
      "text": "كَلَّآ إِنَّ ٱلْإِنسَٰنَ لَيَطْغَىٰٓ",
      "juz": 30,
      "page": 597,
      "tafsir": {
        "muyassar": "حقًا إن الإنسان ليتجاوز حدود الله إذا أبطره الغنى، فليعلم كل طاغية أن المصير إلى الله، فيجازي كلَّ إنسان بعمله.",
        "mukhtasar": "",
        "saadi": "",
        "jalalayn": ""
      },
      "gharib": {
        "muyassar": {},
        "siraj": {}
      }
    },
    {
      "number": 7,
      "text": "أَن رَّءَاهُ ٱسْتَغْنَىٰٓ",
      "juz": 30,
      "page": 597,
      "tafsir": {
        "muyassar": "حقًا إن الإنسان ليتجاوز حدود الله إذا أبطره الغنى، فليعلم كل طاغية أن المصير إلى الله، فيجازي كلَّ إنسان بعمله.",
        "mukhtasar": "",
        "saadi": "",
        "jalalayn": ""
      },
      "gharib": {
        "muyassar": {},
        "siraj": {}
      }
    },
    {
      "number": 8,
      "text": "إِنَّ إِلَىٰ رَبِّكَ ٱلرُّجْعَىٰٓ",
      "juz": 30,
      "page": 597,
      "tafsir": {
        "muyassar": "حقًا إن الإنسان ليتجاوز حدود الله إذا أبطره الغنى، فليعلم كل طاغية أن المصير إلى الله، فيجازي كلَّ إنسان بعمله.",
        "mukhtasar": "",
        "saadi": "",
        "jalalayn": ""
      },
      "gharib": {
        "muyassar": {},
        "siraj": {}
      },
      "video": {
        "videoId": "gf4o7CrmlXk",
        "title": "#برنامج_غريب_القرآن || الحلقة 45 - { فليمدد بسبب إلى السماء }",
        "url": "https://www.youtube.com/watch?v=gf4o7CrmlXk",
        "keyword": "فليمدد بسبب إلى السماء"
      }
    },
    {
      "number": 9,
      "text": "أَرَءَيْتَ ٱلَّذِى يَنْهَىٰ",
      "juz": 30,
      "page": 597,
      "tafsir": {
        "muyassar": "أرأيت أعجب مِن طغيان هذا الرجل (وهو أبو جهل) الذي ينهى عبدًا لنا إذا صلَّى لربه (وهو محمد صلى الله عليه وسلم)؟ أرأيت إن كان المنهي عن الصلاة على الهدى فكيف ينهاه؟ أو إن كان آمرًا غيره بالتقوى أينهاه عن ذلك؟ أرأيت إن كذَّب هذا الناهي بما يُدعى إليه، وأعرض عنه، ألم يعلم بأن الله يرى كل ما يفعل؟ ليس الأمر كما يزعم أبو جهل، لئن لم يرجع هذا عن شقاقه وأذاه لنأخذنَّ بمقدَّم رأسه أخذًا عنيفًا، ويُطرح في النار، ناصيته ناصية كاذبة في مقالها، خاطئة في أفعالها. فليُحْضِر هذا الطاغية أهل ناديه الذين يستنصر بهم، سندعو ملائكة العذاب. ليس الأمر على ما يظن أبو جهل، إنه لن ينالك -أيها الرسول- بسوء، فلا تطعه فيما دعاك إليه مِن تَرْك الصلاة، واسجد لربك واقترب منه بالتحبب إليه بطاعته.",
        "mukhtasar": "",
        "saadi": "",
        "jalalayn": ""
      },
      "gharib": {
        "muyassar": {},
        "siraj": {}
      }
    },
    {
      "number": 10,
      "text": "عَبْدًا إِذَا صَلَّىٰٓ",
      "juz": 30,
      "page": 597,
      "tafsir": {
        "muyassar": "أرأيت أعجب مِن طغيان هذا الرجل (وهو أبو جهل) الذي ينهى عبدًا لنا إذا صلَّى لربه (وهو محمد صلى الله عليه وسلم)؟ أرأيت إن كان المنهي عن الصلاة على الهدى فكيف ينهاه؟ أو إن كان آمرًا غيره بالتقوى أينهاه عن ذلك؟ أرأيت إن كذَّب هذا الناهي بما يُدعى إليه، وأعرض عنه، ألم يعلم بأن الله يرى كل ما يفعل؟ ليس الأمر كما يزعم أبو جهل، لئن لم يرجع هذا عن شقاقه وأذاه لنأخذنَّ بمقدَّم رأسه أخذًا عنيفًا، ويُطرح في النار، ناصيته ناصية كاذبة في مقالها، خاطئة في أفعالها. فليُحْضِر هذا الطاغية أهل ناديه الذين يستنصر بهم، سندعو ملائكة العذاب. ليس الأمر على ما يظن أبو جهل، إنه لن ينالك -أيها الرسول- بسوء، فلا تطعه فيما دعاك إليه مِن تَرْك الصلاة، واسجد لربك واقترب منه بالتحبب إليه بطاعته.",
        "mukhtasar": "",
        "saadi": "",
        "jalalayn": ""
      },
      "gharib": {
        "muyassar": {},
        "siraj": {}
      },
      "video": {
        "videoId": "FqqopePrNYE",
        "title": "برنامج ( غريب القرآن ) || الحلقة 04 - { غاسق إذا وقب }",
        "url": "https://www.youtube.com/watch?v=FqqopePrNYE",
        "keyword": "غاسق إذا وقب"
      }
    },
    {
      "number": 11,
      "text": "أَرَءَيْتَ إِن كَانَ عَلَى ٱلْهُدَىٰٓ",
      "juz": 30,
      "page": 597,
      "tafsir": {
        "muyassar": "أرأيت أعجب مِن طغيان هذا الرجل (وهو أبو جهل) الذي ينهى عبدًا لنا إذا صلَّى لربه (وهو محمد صلى الله عليه وسلم)؟ أرأيت إن كان المنهي عن الصلاة على الهدى فكيف ينهاه؟ أو إن كان آمرًا غيره بالتقوى أينهاه عن ذلك؟ أرأيت إن كذَّب هذا الناهي بما يُدعى إليه، وأعرض عنه، ألم يعلم بأن الله يرى كل ما يفعل؟ ليس الأمر كما يزعم أبو جهل، لئن لم يرجع هذا عن شقاقه وأذاه لنأخذنَّ بمقدَّم رأسه أخذًا عنيفًا، ويُطرح في النار، ناصيته ناصية كاذبة في مقالها، خاطئة في أفعالها. فليُحْضِر هذا الطاغية أهل ناديه الذين يستنصر بهم، سندعو ملائكة العذاب. ليس الأمر على ما يظن أبو جهل، إنه لن ينالك -أيها الرسول- بسوء، فلا تطعه فيما دعاك إليه مِن تَرْك الصلاة، واسجد لربك واقترب منه بالتحبب إليه بطاعته.",
        "mukhtasar": "",
        "saadi": "",
        "jalalayn": ""
      },
      "gharib": {
        "muyassar": {},
        "siraj": {}
      },
      "video": {
        "videoId": "lFySgeRmJQI",
        "title": "#برنامج_غريب_القرآن || الحلقة 61 - { وَلَوْ كَانَ بِهِمْ خَصَاصَةٌ }",
        "url": "https://www.youtube.com/watch?v=lFySgeRmJQI",
        "keyword": "وَلَوْ كَانَ بِهِمْ خَصَاصَةٌ"
      }
    },
    {
      "number": 12,
      "text": "أَوْ أَمَرَ بِٱلتَّقْوَىٰٓ",
      "juz": 30,
      "page": 597,
      "tafsir": {
        "muyassar": "أرأيت أعجب مِن طغيان هذا الرجل (وهو أبو جهل) الذي ينهى عبدًا لنا إذا صلَّى لربه (وهو محمد صلى الله عليه وسلم)؟ أرأيت إن كان المنهي عن الصلاة على الهدى فكيف ينهاه؟ أو إن كان آمرًا غيره بالتقوى أينهاه عن ذلك؟ أرأيت إن كذَّب هذا الناهي بما يُدعى إليه، وأعرض عنه، ألم يعلم بأن الله يرى كل ما يفعل؟ ليس الأمر كما يزعم أبو جهل، لئن لم يرجع هذا عن شقاقه وأذاه لنأخذنَّ بمقدَّم رأسه أخذًا عنيفًا، ويُطرح في النار، ناصيته ناصية كاذبة في مقالها، خاطئة في أفعالها. فليُحْضِر هذا الطاغية أهل ناديه الذين يستنصر بهم، سندعو ملائكة العذاب. ليس الأمر على ما يظن أبو جهل، إنه لن ينالك -أيها الرسول- بسوء، فلا تطعه فيما دعاك إليه مِن تَرْك الصلاة، واسجد لربك واقترب منه بالتحبب إليه بطاعته.",
        "mukhtasar": "",
        "saadi": "",
        "jalalayn": ""
      },
      "gharib": {
        "muyassar": {},
        "siraj": {}
      }
    },
    {
      "number": 13,
      "text": "أَرَءَيْتَ إِن كَذَّبَ وَتَوَلَّىٰٓ",
      "juz": 30,
      "page": 597,
      "tafsir": {
        "muyassar": "أرأيت أعجب مِن طغيان هذا الرجل (وهو أبو جهل) الذي ينهى عبدًا لنا إذا صلَّى لربه (وهو محمد صلى الله عليه وسلم)؟ أرأيت إن كان المنهي عن الصلاة على الهدى فكيف ينهاه؟ أو إن كان آمرًا غيره بالتقوى أينهاه عن ذلك؟ أرأيت إن كذَّب هذا الناهي بما يُدعى إليه، وأعرض عنه، ألم يعلم بأن الله يرى كل ما يفعل؟ ليس الأمر كما يزعم أبو جهل، لئن لم يرجع هذا عن شقاقه وأذاه لنأخذنَّ بمقدَّم رأسه أخذًا عنيفًا، ويُطرح في النار، ناصيته ناصية كاذبة في مقالها، خاطئة في أفعالها. فليُحْضِر هذا الطاغية أهل ناديه الذين يستنصر بهم، سندعو ملائكة العذاب. ليس الأمر على ما يظن أبو جهل، إنه لن ينالك -أيها الرسول- بسوء، فلا تطعه فيما دعاك إليه مِن تَرْك الصلاة، واسجد لربك واقترب منه بالتحبب إليه بطاعته.",
        "mukhtasar": "",
        "saadi": "",
        "jalalayn": ""
      },
      "gharib": {
        "muyassar": {},
        "siraj": {}
      }
    },
    {
      "number": 14,
      "text": "أَلَمْ يَعْلَم بِأَنَّ ٱللَّهَ يَرَىٰ",
      "juz": 30,
      "page": 597,
      "tafsir": {
        "muyassar": "أرأيت أعجب مِن طغيان هذا الرجل (وهو أبو جهل) الذي ينهى عبدًا لنا إذا صلَّى لربه (وهو محمد صلى الله عليه وسلم)؟ أرأيت إن كان المنهي عن الصلاة على الهدى فكيف ينهاه؟ أو إن كان آمرًا غيره بالتقوى أينهاه عن ذلك؟ أرأيت إن كذَّب هذا الناهي بما يُدعى إليه، وأعرض عنه، ألم يعلم بأن الله يرى كل ما يفعل؟ ليس الأمر كما يزعم أبو جهل، لئن لم يرجع هذا عن شقاقه وأذاه لنأخذنَّ بمقدَّم رأسه أخذًا عنيفًا، ويُطرح في النار، ناصيته ناصية كاذبة في مقالها، خاطئة في أفعالها. فليُحْضِر هذا الطاغية أهل ناديه الذين يستنصر بهم، سندعو ملائكة العذاب. ليس الأمر على ما يظن أبو جهل، إنه لن ينالك -أيها الرسول- بسوء، فلا تطعه فيما دعاك إليه مِن تَرْك الصلاة، واسجد لربك واقترب منه بالتحبب إليه بطاعته.",
        "mukhtasar": "",
        "saadi": "",
        "jalalayn": ""
      },
      "gharib": {
        "muyassar": {},
        "siraj": {}
      },
      "video": {
        "videoId": "Yh9ekFRRaU8",
        "title": "#برنامج_غريب_القرآن || الحلقة 81 - { سُجَّدًا لِّلَّهِ وَهُمْ دَاخِرُونَ }",
        "url": "https://www.youtube.com/watch?v=Yh9ekFRRaU8",
        "keyword": "سُجَّدًا لِّلَّهِ وَهُمْ دَاخِرُونَ"
      }
    },
    {
      "number": 15,
      "text": "كَلَّا لَئِن لَّمْ يَنتَهِ لَنَسْفَعًۢا بِٱلنَّاصِيَةِ",
      "juz": 30,
      "page": 597,
      "tafsir": {
        "muyassar": "أرأيت أعجب مِن طغيان هذا الرجل (وهو أبو جهل) الذي ينهى عبدًا لنا إذا صلَّى لربه (وهو محمد صلى الله عليه وسلم)؟ أرأيت إن كان المنهي عن الصلاة على الهدى فكيف ينهاه؟ أو إن كان آمرًا غيره بالتقوى أينهاه عن ذلك؟ أرأيت إن كذَّب هذا الناهي بما يُدعى إليه، وأعرض عنه، ألم يعلم بأن الله يرى كل ما يفعل؟ ليس الأمر كما يزعم أبو جهل، لئن لم يرجع هذا عن شقاقه وأذاه لنأخذنَّ بمقدَّم رأسه أخذًا عنيفًا، ويُطرح في النار، ناصيته ناصية كاذبة في مقالها، خاطئة في أفعالها. فليُحْضِر هذا الطاغية أهل ناديه الذين يستنصر بهم، سندعو ملائكة العذاب. ليس الأمر على ما يظن أبو جهل، إنه لن ينالك -أيها الرسول- بسوء، فلا تطعه فيما دعاك إليه مِن تَرْك الصلاة، واسجد لربك واقترب منه بالتحبب إليه بطاعته.",
        "mukhtasar": "",
        "saadi": "",
        "jalalayn": ""
      },
      "gharib": {
        "muyassar": {},
        "siraj": {}
      },
      "video": {
        "videoId": "9Z55NwEhLjU",
        "title": "برنامج غريب القرآن || الحلقة 44 - { وقالوا ربنا عجل لنا قطنا }",
        "url": "https://www.youtube.com/watch?v=9Z55NwEhLjU",
        "keyword": "وقالوا ربنا عجل لنا قطنا"
      }
    },
    {
      "number": 16,
      "text": "نَاصِيَةٍۢ كَٰذِبَةٍ خَاطِئَةٍۢ",
      "juz": 30,
      "page": 597,
      "tafsir": {
        "muyassar": "أرأيت أعجب مِن طغيان هذا الرجل (وهو أبو جهل) الذي ينهى عبدًا لنا إذا صلَّى لربه (وهو محمد صلى الله عليه وسلم)؟ أرأيت إن كان المنهي عن الصلاة على الهدى فكيف ينهاه؟ أو إن كان آمرًا غيره بالتقوى أينهاه عن ذلك؟ أرأيت إن كذَّب هذا الناهي بما يُدعى إليه، وأعرض عنه، ألم يعلم بأن الله يرى كل ما يفعل؟ ليس الأمر كما يزعم أبو جهل، لئن لم يرجع هذا عن شقاقه وأذاه لنأخذنَّ بمقدَّم رأسه أخذًا عنيفًا، ويُطرح في النار، ناصيته ناصية كاذبة في مقالها، خاطئة في أفعالها. فليُحْضِر هذا الطاغية أهل ناديه الذين يستنصر بهم، سندعو ملائكة العذاب. ليس الأمر على ما يظن أبو جهل، إنه لن ينالك -أيها الرسول- بسوء، فلا تطعه فيما دعاك إليه مِن تَرْك الصلاة، واسجد لربك واقترب منه بالتحبب إليه بطاعته.",
        "mukhtasar": "",
        "saadi": "",
        "jalalayn": ""
      },
      "gharib": {
        "muyassar": {},
        "siraj": {}
      }
    },
    {
      "number": 17,
      "text": "فَلْيَدْعُ نَادِيَهُۥ",
      "juz": 30,
      "page": 597,
      "tafsir": {
        "muyassar": "أرأيت أعجب مِن طغيان هذا الرجل (وهو أبو جهل) الذي ينهى عبدًا لنا إذا صلَّى لربه (وهو محمد صلى الله عليه وسلم)؟ أرأيت إن كان المنهي عن الصلاة على الهدى فكيف ينهاه؟ أو إن كان آمرًا غيره بالتقوى أينهاه عن ذلك؟ أرأيت إن كذَّب هذا الناهي بما يُدعى إليه، وأعرض عنه، ألم يعلم بأن الله يرى كل ما يفعل؟ ليس الأمر كما يزعم أبو جهل، لئن لم يرجع هذا عن شقاقه وأذاه لنأخذنَّ بمقدَّم رأسه أخذًا عنيفًا، ويُطرح في النار، ناصيته ناصية كاذبة في مقالها، خاطئة في أفعالها. فليُحْضِر هذا الطاغية أهل ناديه الذين يستنصر بهم، سندعو ملائكة العذاب. ليس الأمر على ما يظن أبو جهل، إنه لن ينالك -أيها الرسول- بسوء، فلا تطعه فيما دعاك إليه مِن تَرْك الصلاة، واسجد لربك واقترب منه بالتحبب إليه بطاعته.",
        "mukhtasar": "",
        "saadi": "",
        "jalalayn": ""
      },
      "gharib": {
        "muyassar": {},
        "siraj": {}
      }
    },
    {
      "number": 18,
      "text": "سَنَدْعُ ٱلزَّبَانِيَةَ",
      "juz": 30,
      "page": 597,
      "tafsir": {
        "muyassar": "أرأيت أعجب مِن طغيان هذا الرجل (وهو أبو جهل) الذي ينهى عبدًا لنا إذا صلَّى لربه (وهو محمد صلى الله عليه وسلم)؟ أرأيت إن كان المنهي عن الصلاة على الهدى فكيف ينهاه؟ أو إن كان آمرًا غيره بالتقوى أينهاه عن ذلك؟ أرأيت إن كذَّب هذا الناهي بما يُدعى إليه، وأعرض عنه، ألم يعلم بأن الله يرى كل ما يفعل؟ ليس الأمر كما يزعم أبو جهل، لئن لم يرجع هذا عن شقاقه وأذاه لنأخذنَّ بمقدَّم رأسه أخذًا عنيفًا، ويُطرح في النار، ناصيته ناصية كاذبة في مقالها، خاطئة في أفعالها. فليُحْضِر هذا الطاغية أهل ناديه الذين يستنصر بهم، سندعو ملائكة العذاب. ليس الأمر على ما يظن أبو جهل، إنه لن ينالك -أيها الرسول- بسوء، فلا تطعه فيما دعاك إليه مِن تَرْك الصلاة، واسجد لربك واقترب منه بالتحبب إليه بطاعته.",
        "mukhtasar": "",
        "saadi": "",
        "jalalayn": ""
      },
      "gharib": {
        "muyassar": {},
        "siraj": {}
      },
      "video": {
        "videoId": "fBbo0TV-8gg",
        "title": "#برنامج_غريب_القرآن || الحلقة 52 - {تُسْقَىٰ مِنْ عَيْنٍ آنِيَةٍ}",
        "url": "https://www.youtube.com/watch?v=fBbo0TV-8gg",
        "keyword": "تُسْقَىٰ مِنْ عَيْنٍ آنِيَةٍ"
      }
    },
    {
      "number": 19,
      "text": "كَلَّا لَا تُطِعْهُ وَٱسْجُدْ وَٱقْتَرِب ۩",
      "juz": 30,
      "page": 597,
      "tafsir": {
        "muyassar": "أرأيت أعجب مِن طغيان هذا الرجل (وهو أبو جهل) الذي ينهى عبدًا لنا إذا صلَّى لربه (وهو محمد صلى الله عليه وسلم)؟ أرأيت إن كان المنهي عن الصلاة على الهدى فكيف ينهاه؟ أو إن كان آمرًا غيره بالتقوى أينهاه عن ذلك؟ أرأيت إن كذَّب هذا الناهي بما يُدعى إليه، وأعرض عنه، ألم يعلم بأن الله يرى كل ما يفعل؟ ليس الأمر كما يزعم أبو جهل، لئن لم يرجع هذا عن شقاقه وأذاه لنأخذنَّ بمقدَّم رأسه أخذًا عنيفًا، ويُطرح في النار، ناصيته ناصية كاذبة في مقالها، خاطئة في أفعالها. فليُحْضِر هذا الطاغية أهل ناديه الذين يستنصر بهم، سندعو ملائكة العذاب. ليس الأمر على ما يظن أبو جهل، إنه لن ينالك -أيها الرسول- بسوء، فلا تطعه فيما دعاك إليه مِن تَرْك الصلاة، واسجد لربك واقترب منه بالتحبب إليه بطاعته.",
        "mukhtasar": "",
        "saadi": "",
        "jalalayn": ""
      },
      "gharib": {
        "muyassar": {},
        "siraj": {}
      }
    }
  ],
  "tafsirSources": [
    {
      "id": "muyassar",
      "name": "التفسير الميسر",
      "author": "مجمع الملك فهد"
    },
    {
      "id": "mukhtasar",
      "name": "المختصر في التفسير",
      "author": "مركز تفسير"
    },
    {
      "id": "saadi",
      "name": "تفسير السعدي",
      "author": "الشيخ عبدالرحمن السعدي"
    },
    {
      "id": "jalalayn",
      "name": "تفسير الجلالين",
      "author": "جلال الدين المحلي والسيوطي"
    }
  ],
  "gharibSources": [
    {
      "id": "muyassar",
      "name": "الميسر في غريب القرآن",
      "author": "مجمع الملك فهد"
    },
    {
      "id": "siraj",
      "name": "السراج في غريب القرآن",
      "author": "د. محمد الخضيري"
    }
  ],
  "videos": []
}